{
    "location1": {
        "latlong":[43.3134, -90.9445],
        "name":"Potential Sinkhole Cluster",
        "description":"View a series of potential sinkholes.",
        "basemap":"SW WI Hillshade"
    },
    "location2": {
        "latlong":[43.3185, -90.9605],
        "name":"Catchment",
        "description":"View a clear example a catchment basin.",
        "basemap":"SW WI Hillshade"
    }
    "location3": {
        "latlong":[43.3193, -90.7381],
        "name":"Blind Valley",
        "description":"View an example of a blind valley.",
        "basemap":"SW WI Hillshade"
    }
    "location4": {
        "latlong":[43.3258, -90.7238],
        "name":"Sinkhole Line",
        "description":"A line of sinkholes.",
        "basemap":"SW WI Hillshade"
    }
}